{
    "hello": {
        "password": "2",
        "balance": 50,
        "games": []
    },
    "hello1": {
        "password": "eee1",
        "balance": 50,
        "games": []
    },
    "hello111": {
        "password": "11",
        "balance": 50,
        "games": []
    },
    "eeeeeeee": {
        "password": "eeeeeee",
        "balance": 50,
        "games": []
    },
    "rahila": {
        "password": "kamran",
        "balance": 50,
        "games": []
    },
    "2 ci gun 16:45-18:15\n4 cu gun 16:45-18:15": {
        "password": "2 ci gun 16:45-18:15\n4 cu gun 16:45-18:15",
        "balance": 50,
        "games": []
    },
    "2 ci gun 16:45-18:15\n4 cu gun 16:45-18:152 ci gun 16:45-18:15\n4 cu gun 16:45-18:152 ci gun 16:45-18:15\n4 cu gun 16:45-18:15": {
        "password": "2 ci gun 16:45-18:15\n4 cu gun 16:45-18:15",
        "balance": 50,
        "games": []
    },
    "wwjwwjjw": {
        "password": "wwjwwjjw",
        "balance": 50,
        "games": []
    },
    "QQQ": {
        "password": "QQQ",
        "balance": 50,
        "games": []
    },
    "eee": {
        "password": "eee",
        "balance": 50,
        "games": []
    }
}